create_python_app/__init__.py
create_python_app/config.py
create_python_app/create_config_files.py
create_python_app/create_config_module.py
create_python_app/create_gitignore_file.py
create_python_app/create_license_file.py
create_python_app/create_makefile_file.py
create_python_app/create_readme_file.py
create_python_app/create_requirements_file.py
create_python_app/create_root_package.py
create_python_app/create_setup_file.py
create_python_app/main.py
create_python_app/path_utils.py
create_python_app-0.3.3.dist-info/METADATA
create_python_app-0.3.3.dist-info/RECORD
create_python_app-0.3.3.dist-info/WHEEL
create_python_app-0.3.3.dist-info/entry_points.txt
create_python_app-0.3.3.dist-info/top_level.txt
