Metadata-Version: 2.1
Name: create-python-app
Version: 0.3.3
Summary: A tool for creating python apps.
Home-page: https://github.com/xuchaoqian/create-python-app.git
Author: Xu Chaoqian
Author-email: chaoranxu@gmail.com
License: UNKNOWN
Platform: UNKNOWN
Classifier: Programming Language :: Python :: 3
Classifier: License :: OSI Approved :: MIT License
Classifier: Operating System :: OS Independent
